template_nvim/__init__.py
template_nvim-0.1.0.dist-info/WHEEL
template_nvim-0.1.0.dist-info/METADATA
template_nvim-0.1.0.dist-info/RECORD
